limitless_sdk/__init__.py
limitless_sdk/client.py
limitless_sdk/exceptions.py
limitless_sdk/models.py
limitless_sdk/api/__init__.py
limitless_sdk/api/errors.py
limitless_sdk/api/http_client.py
limitless_sdk/api/retry.py
limitless_sdk/auth/__init__.py
limitless_sdk/auth/authenticated_client.py
limitless_sdk/auth/authenticator.py
limitless_sdk/auth/signer.py
limitless_sdk/markets/__init__.py
limitless_sdk/markets/fetcher.py
limitless_sdk/orders/__init__.py
limitless_sdk/orders/builder.py
limitless_sdk/orders/client.py
limitless_sdk/orders/signer.py
limitless_sdk/portfolio/__init__.py
limitless_sdk/portfolio/fetcher.py
limitless_sdk/types/__init__.py
limitless_sdk/types/auth.py
limitless_sdk/types/logger.py
limitless_sdk/types/markets.py
limitless_sdk/types/orders.py
limitless_sdk/types/portfolio.py
limitless_sdk/utils/__init__.py
limitless_sdk/utils/constants.py
limitless_sdk/websocket/__init__.py
limitless_sdk/websocket/client.py
limitless_sdk/websocket/types.py
limitless_sdk-0.4.1.dist-info/licenses/LICENSE
limitless_sdk-0.4.1.dist-info/METADATA
limitless_sdk-0.4.1.dist-info/WHEEL
limitless_sdk-0.4.1.dist-info/top_level.txt
limitless_sdk-0.4.1.dist-info/RECORD
