Metadata-Version: 2.4
Name: limitless-sdk
Version: 0.4.1
Summary: Python SDK for Limitless Exchange
Author-email: Limitless <support@limitless.ai>
License-Expression: MIT
Requires-Python: >=3.8
License-File: LICENSE
Requires-Dist: aiohttp>=3.8.0
Requires-Dist: eth-abi>=5.2.0
Requires-Dist: eth-account>=0.9.0
Requires-Dist: eth-utils>=5.3.0
Requires-Dist: pydantic>=2.0.0
Requires-Dist: python-dotenv>=1.0.1
Requires-Dist: python-socketio>=5.11.0
Provides-Extra: dev
Requires-Dist: pytest; extra == "dev"
Requires-Dist: ruff; extra == "dev"
Requires-Dist: mypy; extra == "dev"
Requires-Dist: pytest-asyncio; extra == "dev"
Dynamic: license-file
